Metadata-Version: 2.1
Name: ewdm
Version: 1.0
Summary: EWDM: A package for a wavelet-based directional wave spectra
Author: Daniel Peláez-Zapata
Author-email: Daniel Peláez-Zapata <daniel.pelaez-zapata@ucdconnect.ie>
Project-URL: documentation, https://extended-wdm.readthedocs.io/en/latest/
Classifier: Intended Audience :: Science/Research
Classifier: License :: OSI Approved :: MIT License
Classifier: Natural Language :: English
Classifier: Operating System :: OS Independent
Classifier: Topic :: Scientific/Engineering
Classifier: Topic :: Scientific/Engineering :: Physics
Classifier: Topic :: Scientific/Engineering :: Visualization
Classifier: Programming Language :: Python :: 3
Classifier: Programming Language :: Python :: 3.8
Classifier: Programming Language :: Python :: 3.9
Classifier: Programming Language :: Python :: 3.10
Classifier: Programming Language :: Python :: 3.11
Classifier: Programming Language :: Python :: 3.12
Requires-Python: >=3.8
License-File: LICENSE
Requires-Dist: numpy
Requires-Dist: scipy
Requires-Dist: matplotlib
Requires-Dist: pandas
Requires-Dist: xarray
Requires-Dist: pydap
Requires-Dist: netCDF4
Requires-Dist: bottleneck
Requires-Dist: tqdm
Provides-Extra: test
Requires-Dist: pytest; extra == "test"
Requires-Dist: flake8; extra == "test"
Provides-Extra: extra
Requires-Dist: zarr; extra == "extra"
Provides-Extra: docs
Requires-Dist: sphinx; extra == "docs"
Requires-Dist: sphinx-rtd-theme; extra == "docs"
Requires-Dist: sphinx-gallery; extra == "docs"
Requires-Dist: autodoc; extra == "docs"
